frechet/__init__.py
frechet/estimators.py
frechet-0.0.1.dist-info/LICENSE
frechet-0.0.1.dist-info/METADATA
frechet-0.0.1.dist-info/WHEEL
frechet-0.0.1.dist-info/top_level.txt
frechet-0.0.1.dist-info/RECORD
